<?xml version="1.0" encoding="UTF-8"?>
<OldCards
        xmlns:xsi="http://www.w3.org/2001/XMLSchema-instance"
        xmlns="http://www.itacademy.by/parshin/OldCards"
        xsi:schemaLocation="http://www.itacademy.by/parshin/OldCards postcards.xsd">

    <postcard_in_the_museum postcard_id="GBR708">
        <theme>Great people quotes</theme>
        <year>2003</year>
        <type>Patriotic postcards</type>
        <country>United Kingdom</country>
        <valuable>Collectible</valuable>
        <museum_name>Louvre</museum_name>
        <museum_location>Paris</museum_location>
    </postcard_in_the_museum>

    <postcard_in_the_museum postcard_id="USA105">
        <theme>Cityscape</theme>
        <year>2001</year>
        <type>Advertising postcards</type>
        <country>United States</country>
        <valuable>Thematic</valuable>
        <museum_name>Louvre</museum_name>
        <museum_location>Paris</museum_location>
    </postcard_in_the_museum>

    <postcard_in_a_private_collection postcard_id="AUS609">
        <theme>Architecture</theme>
        <year>2008</year>
        <type>Photo postcard</type>
        <country>Australia</country>
        <valuable>Historical</valuable>
        <collectors_name>Wildenstein Collection</collectors_name>
        <collection_location>New York</collection_location>
    </postcard_in_a_private_collection>

    <postcard_in_the_museum postcard_id="ITA710">
        <theme>Great people quotes</theme>
        <year>2003</year>
        <type>Business postcard</type>
        <country>Italy</country>
        <valuable>Collectible</valuable>
        <museum_name>Louvre</museum_name>
        <museum_location>Paris</museum_location>
    </postcard_in_the_museum>

    <postcard_in_the_museum postcard_id="IND304">
        <theme>People</theme>
        <year>2007</year>
        <type>Artistic postcards</type>
        <country>India</country>
        <valuable>Thematic</valuable>
        <museum_name>Louvre</museum_name>
        <museum_location>Paris</museum_location>
    </postcard_in_the_museum>

    <postcard_in_a_private_collection postcard_id="EGY01">
        <theme>Architecture</theme>
        <year>1906</year>
        <type>Handmade postcards</type>
        <country>Egypt</country>
        <valuable>Collectible</valuable>
        <collectors_name>Wildenstein Collection</collectors_name>
        <collection_location>New York</collection_location>
    </postcard_in_a_private_collection>

    <postcard_in_the_museum postcard_id="GBR01">
        <theme>Nature</theme>
        <year>2003</year>
        <type>Postcards-reproductions</type>
        <country>Iceland</country>
        <valuable>Collectible</valuable>
        <museum_name>Louvre</museum_name>
        <museum_location>Paris</museum_location>
    </postcard_in_the_museum>

    <postcard_in_the_museum postcard_id="PLW110">
        <theme>Cityscape</theme>
        <year>2016</year>
        <type>Photo postcard</type>
        <country>Palau</country>
        <valuable>Collectible</valuable>
        <museum_name>Louvre</museum_name>
        <museum_location>Paris</museum_location>
    </postcard_in_the_museum>

    <postcard_in_a_private_collection postcard_id="JPN610">
        <theme>Architecture</theme>
        <year>2009</year>
        <type>Photo postcard</type>
        <country>Japan</country>
        <valuable>Historical</valuable>
        <collectors_name>Wildenstein Collection</collectors_name>
        <collection_location>New York</collection_location>
    </postcard_in_a_private_collection>

    <postcard_in_a_private_collection postcard_id="CHN505">
        <theme>Sport</theme>
        <year>2020</year>
        <type>Advertising postcards</type>
        <country>China</country>
        <valuable>Collectible</valuable>
        <collectors_name>Wildenstein Collection</collectors_name>
        <collection_location>New York</collection_location>
    </postcard_in_a_private_collection>

    <postcard_in_the_museum postcard_id="USA307">
        <theme>People</theme>
        <year>2016</year>
        <type>Political postcards</type>
        <country>United States</country>
        <valuable>Thematic</valuable>
        <museum_name>Louvre</museum_name>
        <museum_location>Paris</museum_location>
    </postcard_in_the_museum>

    <postcard_in_a_private_collection postcard_id="ISR402">
        <theme>Religion</theme>
        <year>1969</year>
        <type>A view postcards</type>
        <country>Israel</country>
        <valuable>Thematic</valuable>
        <collectors_name>Wildenstein Collection</collectors_name>
        <collection_location>New York</collection_location>
    </postcard_in_a_private_collection>

    <postcard_in_the_museum postcard_id="RUS204" author="Фёдор Ильич Трофимов">
        <theme>Nature</theme>
        <year>1974</year>
        <type>Artistic postcards</type>
        <country>United Kingdom</country>
        <valuable>Collectible</valuable>
        <museum_name>Louvre</museum_name>
        <museum_location>Paris</museum_location>
    </postcard_in_the_museum>

    <postcard_in_a_private_collection postcard_id="KAZ401">
        <theme>Religion</theme>
        <year>2014</year>
        <type>Greeting Cards</type>
        <country>Kazakhstan</country>
        <valuable>Thematic</valuable>
        <collectors_name>Wildenstein Collection</collectors_name>
        <collection_location>New York</collection_location>
    </postcard_in_a_private_collection>

    <postcard_in_the_museum postcard_id="COM206">
        <theme>Nature</theme>
        <year>2003</year>
        <type>Historical-event postcards</type>
        <country>Comoros</country>
        <valuable>Historical</valuable>
        <museum_name>Louvre</museum_name>
        <museum_location>Paris</museum_location>
    </postcard_in_the_museum>

    <postcard_in_a_private_collection postcard_id="IND409">
        <theme>Religion</theme>
        <year>2014</year>
        <type>Patriotic postcards</type>
        <country>India</country>
        <valuable>Thematic</valuable>
        <collectors_name>Wildenstein Collection</collectors_name>
        <collection_location>New York</collection_location>
    </postcard_in_a_private_collection>

    <postcard_in_the_museum postcard_id="RUS511">
        <theme>Sport</theme>
        <year>2014</year>
        <type>Handmade postcards</type>
        <country>Russian Federation</country>
        <valuable>Historical</valuable>
        <museum_name>Louvre</museum_name>
        <museum_location>Paris</museum_location>
    </postcard_in_the_museum>

    <postcard_in_the_museum postcard_id="COK710">
        <theme>Great people quotes</theme>
        <year>2011</year>
        <type>Business postcard</type>
        <country>Cook Islands</country>
        <valuable>Historical</valuable>
        <museum_name>Louvre</museum_name>
        <museum_location>Paris</museum_location>
    </postcard_in_the_museum>
</OldCards>